cluster/__init__.py
cluster/algorithm.py
cluster_lee-0.0.dev0.dist-info/METADATA
cluster_lee-0.0.dev0.dist-info/WHEEL
cluster_lee-0.0.dev0.dist-info/entry_points.txt
cluster_lee-0.0.dev0.dist-info/top_level.txt
cluster_lee-0.0.dev0.dist-info/RECORD
